async_tio/__init__.py
async_tio/exceptions.py
async_tio/models.py
async_tio/response.py
async_tio/tio.py
async_tio-1.3.2.dist-info/LICENSE
async_tio-1.3.2.dist-info/METADATA
async_tio-1.3.2.dist-info/WHEEL
async_tio-1.3.2.dist-info/top_level.txt
async_tio-1.3.2.dist-info/zip-safe
async_tio-1.3.2.dist-info/RECORD
