Metadata-Version: 2.1
Name: async-tio
Version: 1.3.2
Summary: An unoffical API wrapper for tio.run
Home-page: https://github.com/Tom-the-Bomb/async-tio
Author: Tom-the-Bomb
License: MIT
Project-URL: Repository, https://github.com/Tom-the-Bomb/async-tio
Project-URL: Issue tracker, https://github.com/Tom-the-Bomb/async-tio/issues
Platform: UNKNOWN
Classifier: Intended Audience :: Developers
Classifier: Programming Language :: Python
Classifier: Natural Language :: English
Classifier: Programming Language :: Python :: 3.7
Classifier: Programming Language :: Python :: 3.8
Classifier: Programming Language :: Python :: 3.9
Classifier: Topic :: Software Development :: Libraries
Classifier: Topic :: Software Development :: Libraries :: Python Modules
Classifier: Topic :: Utilities
Requires-Python: >=3.8
License-File: LICENSE
Requires-Dist: aiohttp
Requires-Dist: typing-extensions
